# This file is generated by Tools/cases_generator/py_metadata_generator.py
# from:
#   Python/bytecodes.c
# Do not edit!
_specializations = {
    "RESUME": [
        "RESUME_CHECK",
    ],
    "TO_BOOL": [
        "TO_BOOL_ALWAYS_TRUE",
        "TO_BOOL_BOOL",
        "TO_BOOL_INT",
        "TO_BOOL_LIST",
        "TO_BOOL_NONE",
        "TO_BOOL_STR",
    ],
    "BINARY_OP": [
        "BINARY_OP_MULTIPLY_INT",
        "BINARY_OP_ADD_INT",
        "BINARY_OP_SUBTRACT_INT",
        "BINARY_OP_MULTIPLY_FLOAT",
        "BINARY_OP_ADD_FLOAT",
        "BINARY_OP_SUBTRACT_FLOAT",
        "BINARY_OP_ADD_UNICODE",
        "BINARY_OP_SUBSCR_LIST_INT",
        "BINARY_OP_SUBSCR_LIST_SLICE",
        "BINARY_OP_SUBSCR_TUPLE_INT",
        "BINARY_OP_SUBSCR_STR_INT",
        "BINARY_OP_SUBSCR_USTR_INT",
        "BINARY_OP_SUBSCR_DICT",
        "BINARY_OP_SUBSCR_GETITEM",
        "BINARY_OP_INPLACE_ADD_UNICODE",
        "BINARY_OP_EXTEND",
        "BINARY_OP_INPLACE_ADD_UNICODE",
    ],
    "STORE_SUBSCR": [
        "STORE_SUBSCR_DICT",
        "STORE_SUBSCR_LIST_INT",
    ],
    "SEND": [
        "SEND_GEN",
    ],
    "UNPACK_SEQUENCE": [
        "UNPACK_SEQUENCE_TWO_TUPLE",
        "UNPACK_SEQUENCE_TUPLE",
        "UNPACK_SEQUENCE_LIST",
    ],
    "STORE_ATTR": [
        "STORE_ATTR_INSTANCE_VALUE",
        "STORE_ATTR_SLOT",
        "STORE_ATTR_WITH_HINT",
    ],
    "LOAD_GLOBAL": [
        "LOAD_GLOBAL_MODULE",
        "LOAD_GLOBAL_BUILTIN",
    ],
    "LOAD_SUPER_ATTR": [
        "LOAD_SUPER_ATTR_ATTR",
        "LOAD_SUPER_ATTR_METHOD",
    ],
    "LOAD_ATTR": [
        "LOAD_ATTR_INSTANCE_VALUE",
        "LOAD_ATTR_MODULE",
        "LOAD_ATTR_WITH_HINT",
        "LOAD_ATTR_SLOT",
        "LOAD_ATTR_CLASS",
        "LOAD_ATTR_CLASS_WITH_METACLASS_CHECK",
        "LOAD_ATTR_PROPERTY",
        "LOAD_ATTR_GETATTRIBUTE_OVERRIDDEN",
        "LOAD_ATTR_METHOD_WITH_VALUES",
        "LOAD_ATTR_METHOD_NO_DICT",
        "LOAD_ATTR_METHOD_LAZY_DICT",
        "LOAD_ATTR_NONDESCRIPTOR_WITH_VALUES",
        "LOAD_ATTR_NONDESCRIPTOR_NO_DICT",
    ],
    "COMPARE_OP": [
        "COMPARE_OP_FLOAT",
        "COMPARE_OP_INT",
        "COMPARE_OP_STR",
    ],
    "CONTAINS_OP": [
        "CONTAINS_OP_SET",
        "CONTAINS_OP_DICT",
    ],
    "JUMP_BACKWARD": [
        "JUMP_BACKWARD_NO_JIT",
        "JUMP_BACKWARD_JIT",
    ],
    "FOR_ITER": [
        "FOR_ITER_LIST",
        "FOR_ITER_TUPLE",
        "FOR_ITER_RANGE",
        "FOR_ITER_GEN",
    ],
    "CALL": [
        "CALL_BOUND_METHOD_EXACT_ARGS",
        "CALL_PY_EXACT_ARGS",
        "CALL_TYPE_1",
        "CALL_STR_1",
        "CALL_TUPLE_1",
        "CALL_BUILTIN_CLASS",
        "CALL_BUILTIN_O",
        "CALL_BUILTIN_FAST",
        "CALL_BUILTIN_FAST_WITH_KEYWORDS",
        "CALL_LEN",
        "CALL_ISINSTANCE",
        "CALL_LIST_APPEND",
        "CALL_METHOD_DESCRIPTOR_O",
        "CALL_METHOD_DESCRIPTOR_FAST_WITH_KEYWORDS",
        "CALL_METHOD_DESCRIPTOR_NOARGS",
        "CALL_METHOD_DESCRIPTOR_FAST",
        "CALL_ALLOC_AND_ENTER_INIT",
        "CALL_PY_GENERAL",
        "CALL_BOUND_METHOD_GENERAL",
        "CALL_NON_PY_GENERAL",
    ],
    "CALL_KW": [
        "CALL_KW_BOUND_METHOD",
        "CALL_KW_PY",
        "CALL_KW_NON_PY",
    ],
    "CALL_FUNCTION_EX": [
        "CALL_EX_PY",
        "CALL_EX_NON_PY_GENERAL",
    ],
}

_specialized_opmap = {
    'BINARY_OP_ADD_FLOAT': 129,
    'BINARY_OP_ADD_INT': 130,
    'BINARY_OP_ADD_UNICODE': 131,
    'BINARY_OP_EXTEND': 132,
    'BINARY_OP_INPLACE_ADD_UNICODE': 3,
    'BINARY_OP_INPLACE_ADD_UNICODE': 3,
    'BINARY_OP_MULTIPLY_FLOAT': 133,
    'BINARY_OP_MULTIPLY_INT': 134,
    'BINARY_OP_SUBSCR_DICT': 135,
    'BINARY_OP_SUBSCR_GETITEM': 136,
    'BINARY_OP_SUBSCR_LIST_INT': 137,
    'BINARY_OP_SUBSCR_LIST_SLICE': 138,
    'BINARY_OP_SUBSCR_STR_INT': 139,
    'BINARY_OP_SUBSCR_TUPLE_INT': 140,
    'BINARY_OP_SUBSCR_USTR_INT': 141,
    'BINARY_OP_SUBTRACT_FLOAT': 142,
    'BINARY_OP_SUBTRACT_INT': 143,
    'CALL_ALLOC_AND_ENTER_INIT': 144,
    'CALL_BOUND_METHOD_EXACT_ARGS': 145,
    'CALL_BOUND_METHOD_GENERAL': 146,
    'CALL_BUILTIN_CLASS': 147,
    'CALL_BUILTIN_FAST': 148,
    'CALL_BUILTIN_FAST_WITH_KEYWORDS': 149,
    'CALL_BUILTIN_O': 150,
    'CALL_EX_NON_PY_GENERAL': 151,
    'CALL_EX_PY': 152,
    'CALL_ISINSTANCE': 153,
    'CALL_KW_BOUND_METHOD': 154,
    'CALL_KW_NON_PY': 155,
    'CALL_KW_PY': 156,
    'CALL_LEN': 157,
    'CALL_LIST_APPEND': 158,
    'CALL_METHOD_DESCRIPTOR_FAST': 159,
    'CALL_METHOD_DESCRIPTOR_FAST_WITH_KEYWORDS': 160,
    'CALL_METHOD_DESCRIPTOR_NOARGS': 161,
    'CALL_METHOD_DESCRIPTOR_O': 162,
    'CALL_NON_PY_GENERAL': 163,
    'CALL_PY_EXACT_ARGS': 164,
    'CALL_PY_GENERAL': 165,
    'CALL_STR_1': 166,
    'CALL_TUPLE_1': 167,
    'CALL_TYPE_1': 168,
    'COMPARE_OP_FLOAT': 169,
    'COMPARE_OP_INT': 170,
    'COMPARE_OP_STR': 171,
    'CONTAINS_OP_DICT': 172,
    'CONTAINS_OP_SET': 173,
    'FOR_ITER_GEN': 174,
    'FOR_ITER_LIST': 175,
    'FOR_ITER_RANGE': 176,
    'FOR_ITER_TUPLE': 177,
    'JUMP_BACKWARD_JIT': 178,
    'JUMP_BACKWARD_NO_JIT': 179,
    'LOAD_ATTR_CLASS': 180,
    'LOAD_ATTR_CLASS_WITH_METACLASS_CHECK': 181,
    'LOAD_ATTR_GETATTRIBUTE_OVERRIDDEN': 182,
    'LOAD_ATTR_INSTANCE_VALUE': 183,
    'LOAD_ATTR_METHOD_LAZY_DICT': 184,
    'LOAD_ATTR_METHOD_NO_DICT': 185,
    'LOAD_ATTR_METHOD_WITH_VALUES': 186,
    'LOAD_ATTR_MODULE': 187,
    'LOAD_ATTR_NONDESCRIPTOR_NO_DICT': 188,
    'LOAD_ATTR_NONDESCRIPTOR_WITH_VALUES': 189,
    'LOAD_ATTR_PROPERTY': 190,
    'LOAD_ATTR_SLOT': 191,
    'LOAD_ATTR_WITH_HINT': 192,
    'LOAD_GLOBAL_BUILTIN': 193,
    'LOAD_GLOBAL_MODULE': 194,
    'LOAD_SUPER_ATTR_ATTR': 195,
    'LOAD_SUPER_ATTR_METHOD': 196,
    'RESUME_CHECK': 197,
    'SEND_GEN': 198,
    'STORE_ATTR_INSTANCE_VALUE': 199,
    'STORE_ATTR_SLOT': 200,
    'STORE_ATTR_WITH_HINT': 201,
    'STORE_SUBSCR_DICT': 202,
    'STORE_SUBSCR_LIST_INT': 203,
    'TO_BOOL_ALWAYS_TRUE': 204,
    'TO_BOOL_BOOL': 205,
    'TO_BOOL_INT': 206,
    'TO_BOOL_LIST': 207,
    'TO_BOOL_NONE': 208,
    'TO_BOOL_STR': 209,
    'UNPACK_SEQUENCE_LIST': 210,
    'UNPACK_SEQUENCE_TUPLE': 211,
    'UNPACK_SEQUENCE_TWO_TUPLE': 212,
}

opmap = {
    'CACHE': 0,
    'RESERVED': 17,
    'RESUME': 128,
    'INSTRUMENTED_LINE': 253,
    'ENTER_EXECUTOR': 254,
    'TRACE_RECORD': 255,
    'BINARY_SLICE': 1,
    'BUILD_TEMPLATE': 2,
    'CALL_FUNCTION_EX': 4,
    'CHECK_EG_MATCH': 5,
    'CHECK_EXC_MATCH': 6,
    'CLEANUP_THROW': 7,
    'DELETE_SUBSCR': 8,
    'END_FOR': 9,
    'END_SEND': 10,
    'EXIT_INIT_CHECK': 11,
    'FORMAT_SIMPLE': 12,
    'FORMAT_WITH_SPEC': 13,
    'GET_AITER': 14,
    'GET_ANEXT': 15,
    'GET_ITER': 16,
    'GET_LEN': 18,
    'GET_YIELD_FROM_ITER': 19,
    'INTERPRETER_EXIT': 20,
    'LOAD_BUILD_CLASS': 21,
    'LOAD_LOCALS': 22,
    'MAKE_FUNCTION': 23,
    'MATCH_CLASS_ISINSTANCE': 24,
    'MATCH_KEYS': 25,
    'MATCH_MAPPING': 26,
    'MATCH_SEQUENCE': 27,
    'NOP': 28,
    'NOT_TAKEN': 29,
    'POP_EXCEPT': 30,
    'POP_ITER': 31,
    'POP_TOP': 32,
    'PUSH_EXC_INFO': 33,
    'PUSH_NULL': 34,
    'RETURN_GENERATOR': 35,
    'RETURN_VALUE': 36,
    'SETUP_ANNOTATIONS': 37,
    'STORE_SLICE': 38,
    'STORE_SUBSCR': 39,
    'TO_BOOL': 40,
    'UNARY_INVERT': 41,
    'UNARY_NEGATIVE': 42,
    'UNARY_NOT': 43,
    'WITH_EXCEPT_START': 44,
    'BINARY_OP': 45,
    'BUILD_INTERPOLATION': 46,
    'BUILD_LIST': 47,
    'BUILD_MAP': 48,
    'BUILD_SET': 49,
    'BUILD_SLICE': 50,
    'BUILD_STRING': 51,
    'BUILD_TUPLE': 52,
    'CALL': 53,
    'CALL_INTRINSIC_1': 54,
    'CALL_INTRINSIC_2': 55,
    'CALL_KW': 56,
    'COMPARE_OP': 57,
    'CONTAINS_OP': 58,
    'CONVERT_VALUE': 59,
    'COPY': 60,
    'COPY_FREE_VARS': 61,
    'DELETE_ATTR': 62,
    'DELETE_DEREF': 63,
    'DELETE_FAST': 64,
    'DELETE_GLOBAL': 65,
    'DELETE_NAME': 66,
    'DICT_MERGE': 67,
    'DICT_UPDATE': 68,
    'END_ASYNC_FOR': 69,
    'EXTENDED_ARG': 70,
    'FOR_ITER': 71,
    'GET_AWAITABLE': 72,
    'IMPORT_FROM': 73,
    'IMPORT_NAME': 74,
    'IS_OP': 75,
    'JUMP_BACKWARD': 76,
    'JUMP_BACKWARD_NO_INTERRUPT': 77,
    'JUMP_FORWARD': 78,
    'LIST_APPEND': 79,
    'LIST_EXTEND': 80,
    'LOAD_ATTR': 81,
    'LOAD_COMMON_CONSTANT': 82,
    'LOAD_CONST': 83,
    'LOAD_DEREF': 84,
    'LOAD_FAST': 85,
    'LOAD_FAST_AND_CLEAR': 86,
    'LOAD_FAST_BORROW': 87,
    'LOAD_FAST_BORROW_LOAD_FAST_BORROW': 88,
    'LOAD_FAST_CHECK': 89,
    'LOAD_FAST_LOAD_FAST': 90,
    'LOAD_FROM_DICT_OR_DEREF': 91,
    'LOAD_FROM_DICT_OR_GLOBALS': 92,
    'LOAD_GLOBAL': 93,
    'LOAD_NAME': 94,
    'LOAD_SMALL_INT': 95,
    'LOAD_SPECIAL': 96,
    'LOAD_SUPER_ATTR': 97,
    'MAKE_CELL': 98,
    'MAP_ADD': 99,
    'MATCH_CLASS': 100,
    'MATCH_CLASS_GET_OPT_ATTR': 101,
    'POP_JUMP_IF_FALSE': 102,
    'POP_JUMP_IF_NONE': 103,
    'POP_JUMP_IF_NOT_NONE': 104,
    'POP_JUMP_IF_TRUE': 105,
    'RAISE_VARARGS': 106,
    'RERAISE': 107,
    'SEND': 108,
    'SET_ADD': 109,
    'SET_FUNCTION_ATTRIBUTE': 110,
    'SET_UPDATE': 111,
    'STORE_ATTR': 112,
    'STORE_DEREF': 113,
    'STORE_FAST': 114,
    'STORE_FAST_LOAD_FAST': 115,
    'STORE_FAST_STORE_FAST': 116,
    'STORE_GLOBAL': 117,
    'STORE_NAME': 118,
    'SWAP': 119,
    'UNPACK_EX': 120,
    'UNPACK_SEQUENCE': 121,
    'YIELD_VALUE': 122,
    'INSTRUMENTED_END_FOR': 233,
    'INSTRUMENTED_POP_ITER': 234,
    'INSTRUMENTED_END_SEND': 235,
    'INSTRUMENTED_FOR_ITER': 236,
    'INSTRUMENTED_INSTRUCTION': 237,
    'INSTRUMENTED_JUMP_FORWARD': 238,
    'INSTRUMENTED_NOT_TAKEN': 239,
    'INSTRUMENTED_POP_JUMP_IF_TRUE': 240,
    'INSTRUMENTED_POP_JUMP_IF_FALSE': 241,
    'INSTRUMENTED_POP_JUMP_IF_NONE': 242,
    'INSTRUMENTED_POP_JUMP_IF_NOT_NONE': 243,
    'INSTRUMENTED_RESUME': 244,
    'INSTRUMENTED_RETURN_VALUE': 245,
    'INSTRUMENTED_YIELD_VALUE': 246,
    'INSTRUMENTED_END_ASYNC_FOR': 247,
    'INSTRUMENTED_LOAD_SUPER_ATTR': 248,
    'INSTRUMENTED_CALL': 249,
    'INSTRUMENTED_CALL_KW': 250,
    'INSTRUMENTED_CALL_FUNCTION_EX': 251,
    'INSTRUMENTED_JUMP_BACKWARD': 252,
    'ANNOTATIONS_PLACEHOLDER': 256,
    'JUMP': 257,
    'JUMP_IF_FALSE': 258,
    'JUMP_IF_TRUE': 259,
    'JUMP_NO_INTERRUPT': 260,
    'LOAD_CLOSURE': 261,
    'POP_BLOCK': 262,
    'SETUP_CLEANUP': 263,
    'SETUP_FINALLY': 264,
    'SETUP_WITH': 265,
    'STORE_FAST_MAYBE_NULL': 266,
}

HAVE_ARGUMENT = 44
MIN_INSTRUMENTED_OPCODE = 233
